pycqs-1.0.1.dist-info/METADATA
pycqs-1.0.1.dist-info/WHEEL
pycqs-1.0.1.dist-info/licenses/LICENSE
pycqs/__init__.py
pycqs/command_bus.py
pycqs/py.typed
pycqs/query_bus.py
pycqs-1.0.1.dist-info/RECORD
